uniprot_id_mapping/__init__.py
uniprot_id_mapping/cache.py
uniprot_id_mapping/exception.py
uniprot_id_mapping/id_mapper.py
uniprot_id_mapping/main.py
uniprot_id_mapping/version.py
uniprot_id_mapping-2024.4.dist-info/METADATA
uniprot_id_mapping-2024.4.dist-info/WHEEL
uniprot_id_mapping-2024.4.dist-info/entry_points.txt
uniprot_id_mapping-2024.4.dist-info/licenses/LICENSE.txt
uniprot_id_mapping-2024.4.dist-info/RECORD
