Metadata-Version: 2.3
Name: uniprot-id_mapping
Version: 2024.4
Summary: A wrapper around the UniProt ID Mapping web service.
Project-URL: Homepage, https://gitlab.inria.fr/jrye/uniprot-id-mapping
Project-URL: Source, https://gitlab.inria.fr/jrye/uniprot-id-mapping.git
Project-URL: Documentation, https://jrye.gitlabpages.inria.fr/uniprot-id-mapping
Project-URL: Issues, https://gitlab.inria.fr/jrye/uniprot-id-mapping/-/issues
Author-email: Jan-Michael Rye <jan-michael.rye@inria.fr>
License: MIT License
Classifier: License :: OSI Approved :: MIT License
Classifier: Operating System :: OS Independent
Classifier: Programming Language :: Python :: 3
Requires-Python: >=3.7
Requires-Dist: pyxdg
Requires-Dist: requests
